takion_api/__init__.py
takion_api/exceptions.py
takion_api/models.py
takion_api/datadome/__init__.py
takion_api/datadome/main.py
takion_api/incapsula/__init__.py
takion_api/incapsula/reese84.py
takion_api/incapsula/utmvc.py
takion_api-0.1.41.dist-info/LICENSE
takion_api-0.1.41.dist-info/METADATA
takion_api-0.1.41.dist-info/WHEEL
takion_api-0.1.41.dist-info/top_level.txt
takion_api-0.1.41.dist-info/RECORD
