Metadata-Version: 2.1
Name: takion_api
Version: 0.1.41
Summary: Official Python wrapper for TakionAPI services, designed for efficient automation and bypass of advanced antibot systems.
Home-page: https://github.com/Takion-API-Services/takion-api
Author: glizzykingdreko
Author-email: glizzykingdreko@protonmail.com
Keywords: takion-api,takion,datadome,antibot,bypass
Classifier: Programming Language :: Python :: 3
Classifier: License :: OSI Approved :: MIT License
Classifier: Operating System :: OS Independent
Requires-Python: >=3.6
License-File: LICENSE
Requires-Dist: certifi ==2023.11.17
Requires-Dist: charset-normalizer ==3.3.2
Requires-Dist: idna ==3.6
Requires-Dist: requests ==2.31.0
Requires-Dist: tls-client ==0.2.2
Requires-Dist: urllib3 ==2.1.0
